<?xml version='1.0' encoding='ISO-8859-1'?>
 <siteData xmlns:xsi="http://www.w3.org/2001/XMLSchema-instance" xsi:noNamespaceSchemaLocation="https://dd.weather.gc.ca/citypage_weather/schema/site.xsd">
 <license>https://dd.weather.gc.ca/doc/LICENCE_GENERAL.txt</license>
 <dateTime name="xmlCreation" zone="UTC" UTCOffset="0">
 <year>2021</year>
 <month name="June">06</month>
 <day name="Tuesday">08</day>
 <hour>17</hour>
 <minute>06</minute>
 <timeStamp>20210608170600</timeStamp>
 <textSummary>Tuesday June 08, 2021 at 17:06 UTC</textSummary>
 </dateTime>
 <dateTime name="xmlCreation" zone="EDT" UTCOffset="-4">
 <year>2021</year>
 <month name="June">06</month>
 <day name="Tuesday">08</day>
 <hour>13</hour>
 <minute>06</minute>
 <timeStamp>20210608130600</timeStamp>
 <textSummary>Tuesday June 08, 2021 at 13:06 EDT</textSummary>
 </dateTime>
 <location>
 <continent>North America</continent>
 <country code="ca">Canada</country>
 <province code="on">Ontario</province>
 <name code="s0000458" lat="43.74N" lon="79.37W">Toronto</name>
 <region>City of Toronto</region>
 </location>
 <warnings/>
 <currentConditions>
 <station code="yyz" lat="43.68N" lon="79.63W">Toronto Pearson Int'l Airport</station>
 <dateTime name="observation" zone="UTC" UTCOffset="0">
 <year>2021</year>
 <month name="June">06</month>
 <day name="Tuesday">08</day>
 <hour>17</hour>
 <minute>00</minute>
 <timeStamp>20210608170000</timeStamp>
 <textSummary>Tuesday June 08, 2021 at 17:00 UTC</textSummary>
 </dateTime>
 <dateTime name="observation" zone="EDT" UTCOffset="-4">
 <year>2021</year>
 <month name="June">06</month>
 <day name="Tuesday">08</day>
 <hour>13</hour>
 <minute>00</minute>
 <timeStamp>20210608130000</timeStamp>
 <textSummary>Tuesday June 08, 2021 at 13:00 EDT</textSummary>
 </dateTime>
 <condition>Mostly Cloudy</condition>
 <iconCode format="gif">03</iconCode>
 <temperature unitType="metric" units="C">24.5</temperature>
 <dewpoint unitType="metric" units="C">22.4</dewpoint>
 <humidex unitType="metric">34</humidex>
 <pressure unitType="metric" units="kPa" change="0.07" tendency="rising">101.7</pressure>
 <visibility unitType="metric" units="km">16.1</visibility>
 <relativeHumidity units="%">88</relativeHumidity>
 <wind>
 <speed unitType="metric" units="km/h">4</speed>
 <gust unitType="metric" units="km/h"/>
 <direction>ESE</direction>
 <bearing units="degrees">113.0</bearing>
 </wind>
 </currentConditions>
 <forecastGroup>
 <dateTime name="forecastIssue" zone="UTC" UTCOffset="0">
 <year>2021</year>
 <month name="June">06</month>
 <day name="Tuesday">08</day>
 <hour>15</hour>
 <minute>39</minute>
 <timeStamp>20210608153900</timeStamp>
 <textSummary>Tuesday June 08, 2021 at 15:39 UTC</textSummary>
 </dateTime>
 <dateTime name="forecastIssue" zone="EDT" UTCOffset="-4">
 <year>2021</year>
 <month name="June">06</month>
 <day name="Tuesday">08</day>
 <hour>11</hour>
 <minute>39</minute>
 <timeStamp>20210608113900</timeStamp>
 <textSummary>Tuesday June 08, 2021 at 11:39 EDT</textSummary>
 </dateTime>
 <regionalNormals>
 <textSummary>Low 13. High 23.</textSummary>
 <temperature unitType="metric" units="C" class="high">23</temperature>
 <temperature unitType="metric" units="C" class="low">13</temperature>
 </regionalNormals>
 <forecast>
 <period textForecastName="Today">Tuesday</period>
 <textSummary>Showers ending early this afternoon then cloudy with 60 percent chance of showers or thunderstorms. High 28. Humidex 36. UV index 5 or moderate.</textSummary>
 <cloudPrecip>
 <textSummary>Showers ending early this afternoon then cloudy with 60 percent chance of showers or thunderstorms.</textSummary>
 </cloudPrecip>
 <abbreviatedForecast>
 <iconCode format="gif">19</iconCode>
 <pop units="%">60</pop>
 <textSummary>Chance of showers or thunderstorms</textSummary>
 </abbreviatedForecast>
 <temperatures>
 <textSummary>High 28.</textSummary>
 <temperature unitType="metric" units="C" class="high">28</temperature>
 </temperatures>
 <winds/>
 <humidex>
 <calculated unitType="metric">36</calculated>
 <textSummary>Humidex 36.</textSummary>
 </humidex>
 <precipitation>
 <textSummary/>
 <precipType start="15" end="22">rain</precipType>
 <accumulation>
 <name>rain</name>
 <amount unitType="metric" units="mm">3</amount>
 </accumulation>
 </precipitation>
 <uv category="moderate">
 <index>5</index>
 <textSummary>UV index 5 or moderate.</textSummary>
 </uv>
 <relativeHumidity units="%">70</relativeHumidity>
 </forecast>
 <forecast>
 <period textForecastName="Tonight">Tuesday night</period>
 <textSummary>Partly cloudy. 30 percent chance of showers early this evening with risk of a thunderstorm. Low 20.</textSummary>
 <cloudPrecip>
 <textSummary>Partly cloudy. 30 percent chance of showers early this evening with risk of a thunderstorm.</textSummary>
 </cloudPrecip>
 <abbreviatedForecast>
 <iconCode format="gif">39</iconCode>
 <pop units="%">30</pop>
 <textSummary>Chance of showers</textSummary>
 </abbreviatedForecast>
 <temperatures>
 <textSummary>Low 20.</textSummary>
 <temperature unitType="metric" units="C" class="low">20</temperature>
 </temperatures>
 <winds/>
 <humidex/>
 <precipitation>
 <textSummary/>
 <precipType start="22" end="24">rain</precipType>
 </precipitation>
 <relativeHumidity units="%">80</relativeHumidity>
 </forecast>
 <forecast>
 <period textForecastName="Wednesday">Wednesday</period>
 <textSummary>A mix of sun and cloud. 30 percent chance of showers in the afternoon. High 30. Humidex 37. UV index 9 or very high.</textSummary>
 <cloudPrecip>
 <textSummary>A mix of sun and cloud. 30 percent chance of showers in the afternoon.</textSummary>
 </cloudPrecip>
 <abbreviatedForecast>
 <iconCode format="gif">06</iconCode>
 <pop units="%">30</pop>
 <textSummary>Chance of showers</textSummary>
 </abbreviatedForecast>
 <temperatures>
 <textSummary>High 30.</textSummary>
 <temperature unitType="metric" units="C" class="high">30</temperature>
 </temperatures>
 <winds/>
 <humidex>
 <calculated unitType="metric">37</calculated>
 <textSummary>Humidex 37.</textSummary>
 </humidex>
 <precipitation>
 <textSummary/>
 <precipType start="40" end="46">rain</precipType>
 </precipitation>
 <uv category="very high">
 <index>9</index>
 <textSummary>UV index 9 or very high.</textSummary>
 </uv>
 <relativeHumidity units="%">60</relativeHumidity>
 </forecast>
 <forecast>
 <period textForecastName="Wednesday night">Wednesday night</period>
 <textSummary>Clear. Low 18.</textSummary>
 <cloudPrecip>
 <textSummary>Clear.</textSummary>
 </cloudPrecip>
 <abbreviatedForecast>
 <iconCode format="gif">30</iconCode>
 <pop units="%"/>
 <textSummary>Clear</textSummary>
 </abbreviatedForecast>
 <temperatures>
 <textSummary>Low 18.</textSummary>
 <temperature unitType="metric" units="C" class="low">18</temperature>
 </temperatures>
 <winds/>
 <humidex/>
 <precipitation>
 <textSummary/>
 <precipType start="" end=""/>
 </precipitation>
 <relativeHumidity units="%">70</relativeHumidity>
 </forecast>
 <forecast>
 <period textForecastName="Thursday">Thursday</period>
 <textSummary>Sunny. High 24.</textSummary>
 <cloudPrecip>
 <textSummary>Sunny.</textSummary>
 </cloudPrecip>
 <abbreviatedForecast>
 <iconCode format="gif">00</iconCode>
 <pop units="%"/>
 <textSummary>Sunny</textSummary>
 </abbreviatedForecast>
 <temperatures>
 <textSummary>High 24.</textSummary>
 <temperature unitType="metric" units="C" class="high">24</temperature>
 </temperatures>
 <winds/>
 <humidex/>
 <precipitation>
 <textSummary/>
 <precipType start="" end=""/>
 </precipitation>
 <relativeHumidity units="%">55</relativeHumidity>
 </forecast>
 <forecast>
 <period textForecastName="Thursday night">Thursday night</period>
 <textSummary>Cloudy periods with 30 percent chance of showers. Low 17.</textSummary>
 <cloudPrecip>
 <textSummary>Cloudy periods with 30 percent chance of showers.</textSummary>
 </cloudPrecip>
 <abbreviatedForecast>
 <iconCode format="gif">36</iconCode>
 <pop units="%">30</pop>
 <textSummary>Chance of showers</textSummary>
 </abbreviatedForecast>
 <temperatures>
 <textSummary>Low 17.</textSummary>
 <temperature unitType="metric" units="C" class="low">17</temperature>
 </temperatures>
 <winds/>
 <humidex/>
 <precipitation>
 <textSummary/>
 <precipType start="78" end="82">rain</precipType>
 </precipitation>
 <relativeHumidity units="%">65</relativeHumidity>
 </forecast>
 <forecast>
 <period textForecastName="Friday">Friday</period>
 <textSummary>A mix of sun and cloud with 30 percent chance of showers. High 22.</textSummary>
 <cloudPrecip>
 <textSummary>A mix of sun and cloud with 30 percent chance of showers.</textSummary>
 </cloudPrecip>
 <abbreviatedForecast>
 <iconCode format="gif">06</iconCode>
 <pop units="%">30</pop>
 <textSummary>Chance of showers</textSummary>
 </abbreviatedForecast>
 <temperatures>
 <textSummary>High 22.</textSummary>
 <temperature unitType="metric" units="C" class="high">22</temperature>
 </temperatures>
 <winds/>
 <humidex/>
 <precipitation>
 <textSummary/>
 <precipType start="82" end="84">rain</precipType>
 </precipitation>
 <relativeHumidity units="%">70</relativeHumidity>
 </forecast>
 <forecast>
 <period textForecastName="Friday night">Friday night</period>
 <textSummary>Cloudy periods. Low 15.</textSummary>
 <cloudPrecip>
 <textSummary>Cloudy periods.</textSummary>
 </cloudPrecip>
 <abbreviatedForecast>
 <iconCode format="gif">32</iconCode>
 <pop units="%"/>
 <textSummary>Cloudy periods</textSummary>
 </abbreviatedForecast>
 <temperatures>
 <textSummary>Low 15.</textSummary>
 <temperature unitType="metric" units="C" class="low">15</temperature>
 </temperatures>
 <winds/>
 <humidex/>
 <precipitation>
 <textSummary/>
 <precipType start="" end=""/>
 </precipitation>
 <relativeHumidity units="%">80</relativeHumidity>
 </forecast>
 <forecast>
 <period textForecastName="Saturday">Saturday</period>
 <textSummary>Sunny. High 23.</textSummary>
 <cloudPrecip>
 <textSummary>Sunny.</textSummary>
 </cloudPrecip>
 <abbreviatedForecast>
 <iconCode format="gif">00</iconCode>
 <pop units="%"/>
 <textSummary>Sunny</textSummary>
 </abbreviatedForecast>
 <temperatures>
 <textSummary>High 23.</textSummary>
 <temperature unitType="metric" units="C" class="high">23</temperature>
 </temperatures>
 <winds/>
 <humidex/>
 <precipitation>
 <textSummary/>
 <precipType start="" end=""/>
 </precipitation>
 <relativeHumidity units="%">55</relativeHumidity>
 </forecast>
 <forecast>
 <period textForecastName="Saturday night">Saturday night</period>
 <textSummary>Clear. Low 15.</textSummary>
 <cloudPrecip>
 <textSummary>Clear.</textSummary>
 </cloudPrecip>
 <abbreviatedForecast>
 <iconCode format="gif">30</iconCode>
 <pop units="%"/>
 <textSummary>Clear</textSummary>
 </abbreviatedForecast>
 <temperatures>
 <textSummary>Low 15.</textSummary>
 <temperature unitType="metric" units="C" class="low">15</temperature>
 </temperatures>
 <winds/>
 <humidex/>
 <precipitation>
 <textSummary/>
 <precipType start="" end=""/>
 </precipitation>
 <relativeHumidity units="%">75</relativeHumidity>
 </forecast>
 <forecast>
 <period textForecastName="Sunday">Sunday</period>
 <textSummary>Sunny. High 24.</textSummary>
 <cloudPrecip>
 <textSummary>Sunny.</textSummary>
 </cloudPrecip>
 <abbreviatedForecast>
 <iconCode format="gif">00</iconCode>
 <pop units="%"/>
 <textSummary>Sunny</textSummary>
 </abbreviatedForecast>
 <temperatures>
 <textSummary>High 24.</textSummary>
 <temperature unitType="metric" units="C" class="high">24</temperature>
 </temperatures>
 <winds/>
 <humidex/>
 <precipitation>
 <textSummary/>
 <precipType start="" end=""/>
 </precipitation>
 <relativeHumidity units="%">55</relativeHumidity>
 </forecast>
 <forecast>
 <period textForecastName="Sunday night">Sunday night</period>
 <textSummary>Clear. Low 15.</textSummary>
 <cloudPrecip>
 <textSummary>Clear.</textSummary>
 </cloudPrecip>
 <abbreviatedForecast>
 <iconCode format="gif">30</iconCode>
 <pop units="%"/>
 <textSummary>Clear</textSummary>
 </abbreviatedForecast>
 <temperatures>
 <textSummary>Low 15.</textSummary>
 <temperature unitType="metric" units="C" class="low">15</temperature>
 </temperatures>
 <winds/>
 <humidex/>
 <precipitation>
 <textSummary/>
 <precipType start="" end=""/>
 </precipitation>
 <relativeHumidity units="%">70</relativeHumidity>
 </forecast>
 <forecast>
 <period textForecastName="Monday">Monday</period>
 <textSummary>Sunny. High 24.</textSummary>
 <cloudPrecip>
 <textSummary>Sunny.</textSummary>
 </cloudPrecip>
 <abbreviatedForecast>
 <iconCode format="gif">00</iconCode>
 <pop units="%"/>
 <textSummary>Sunny</textSummary>
 </abbreviatedForecast>
 <temperatures>
 <textSummary>High 24.</textSummary>
 <temperature unitType="metric" units="C" class="high">24</temperature>
 </temperatures>
 <winds/>
 <humidex/>
 <precipitation>
 <textSummary/>
 <precipType start="" end=""/>
 </precipitation>
 <relativeHumidity units="%">50</relativeHumidity>
 </forecast>
 </forecastGroup>
 <hourlyForecastGroup>
 <dateTime name="forecastIssue" zone="UTC" UTCOffset="0">
 <year>2021</year>
 <month name="June">06</month>
 <day name="Tuesday">08</day>
 <hour>15</hour>
 <minute>39</minute>
 <timeStamp>20210608153900</timeStamp>
 <textSummary>Tuesday June 08, 2021 at 15:39 UTC</textSummary>
 </dateTime>
 <dateTime name="forecastIssue" zone="EDT" UTCOffset="-4">
 <year>2021</year>
 <month name="June">06</month>
 <day name="Tuesday">08</day>
 <hour>11</hour>
 <minute>39</minute>
 <timeStamp>20210608113900</timeStamp>
 <textSummary>Tuesday June 08, 2021 at 11:39 EDT</textSummary>
 </dateTime>
 <hourlyForecast dateTimeUTC="202106081800">
 <condition>Chance of showers or thunderstorms</condition>
 <iconCode format="png">19</iconCode>
 <temperature unitType="metric" units="C">27</temperature>
 <lop category="Medium" units="%">60</lop>
 <windChill unitType="metric"/>
 <humidex unitType="metric">35</humidex>
 <wind>
 <speed unitType="metric" units="km/h">5</speed>
 <direction windDirFull="Variable direction">VR</direction>
 <gust unitType="metric" units="km/h"/>
 </wind>
 </hourlyForecast>
 <hourlyForecast dateTimeUTC="202106081900">
 <condition>Chance of showers or thunderstorms</condition>
 <iconCode format="png">19</iconCode>
 <temperature unitType="metric" units="C">27</temperature>
 <lop category="Medium" units="%">60</lop>
 <windChill unitType="metric"/>
 <humidex unitType="metric">35</humidex>
 <wind>
 <speed unitType="metric" units="km/h">10</speed>
 <direction windDirFull="West">W</direction>
 <gust unitType="metric" units="km/h"/>
 </wind>
 </hourlyForecast>
 <hourlyForecast dateTimeUTC="202106082000">
 <condition>Chance of showers or thunderstorms</condition>
 <iconCode format="png">09</iconCode>
 <temperature unitType="metric" units="C">27</temperature>
 <lop category="Medium" units="%">60</lop>
 <windChill unitType="metric"/>
 <humidex unitType="metric">35</humidex>
 <wind>
 <speed unitType="metric" units="km/h">5</speed>
 <direction windDirFull="Variable direction">VR</direction>
 <gust unitType="metric" units="km/h"/>
 </wind>
 </hourlyForecast>
 <hourlyForecast dateTimeUTC="202106082100">
 <condition>Chance of showers or thunderstorms</condition>
 <iconCode format="png">09</iconCode>
 <temperature unitType="metric" units="C">27</temperature>
 <lop category="Medium" units="%">60</lop>
 <windChill unitType="metric"/>
 <humidex unitType="metric">35</humidex>
 <wind>
 <speed unitType="metric" units="km/h">5</speed>
 <direction windDirFull="Variable direction">VR</direction>
 <gust unitType="metric" units="km/h"/>
 </wind>
 </hourlyForecast>
 <hourlyForecast dateTimeUTC="202106082200">
 <condition>Chance of showers. Risk of thunderstorms</condition>
 <iconCode format="png">09</iconCode>
 <temperature unitType="metric" units="C">27</temperature>
 <lop category="Low" units="%">30</lop>
 <windChill unitType="metric"/>
 <humidex unitType="metric">35</humidex>
 <wind>
 <speed unitType="metric" units="km/h">5</speed>
 <direction windDirFull="Variable direction">VR</direction>
 <gust unitType="metric" units="km/h"/>
 </wind>
 </hourlyForecast>
 <hourlyForecast dateTimeUTC="202106082300">
 <condition>Chance of showers. Risk of thunderstorms</condition>
 <iconCode format="png">09</iconCode>
 <temperature unitType="metric" units="C">28</temperature>
 <lop category="Low" units="%">30</lop>
 <windChill unitType="metric"/>
 <humidex unitType="metric">36</humidex>
 <wind>
 <speed unitType="metric" units="km/h">5</speed>
 <direction windDirFull="Variable direction">VR</direction>
 <gust unitType="metric" units="km/h"/>
 </wind>
 </hourlyForecast>
 <hourlyForecast dateTimeUTC="202106090000">
 <condition>A mix of sun and cloud</condition>
 <iconCode format="png">02</iconCode>
 <temperature unitType="metric" units="C">28</temperature>
 <lop category="Low" units="%">20</lop>
 <windChill unitType="metric"/>
 <humidex unitType="metric">36</humidex>
 <wind>
 <speed unitType="metric" units="km/h">10</speed>
 <direction windDirFull="Southwest">SW</direction>
 <gust unitType="metric" units="km/h"/>
 </wind>
 </hourlyForecast>
 <hourlyForecast dateTimeUTC="202106090100">
 <condition>Partly cloudy</condition>
 <iconCode format="png">32</iconCode>
 <temperature unitType="metric" units="C">27</temperature>
 <lop category="Low" units="%">20</lop>
 <windChill unitType="metric"/>
 <humidex unitType="metric">35</humidex>
 <wind>
 <speed unitType="metric" units="km/h">10</speed>
 <direction windDirFull="Southwest">SW</direction>
 <gust unitType="metric" units="km/h"/>
 </wind>
 </hourlyForecast>
 <hourlyForecast dateTimeUTC="202106090200">
 <condition>Partly cloudy</condition>
 <iconCode format="png">32</iconCode>
 <temperature unitType="metric" units="C">25</temperature>
 <lop category="Low" units="%">20</lop>
 <windChill unitType="metric"/>
 <humidex unitType="metric">33</humidex>
 <wind>
 <speed unitType="metric" units="km/h">10</speed>
 <direction windDirFull="Southwest">SW</direction>
 <gust unitType="metric" units="km/h"/>
 </wind>
 </hourlyForecast>
 <hourlyForecast dateTimeUTC="202106090300">
 <condition>Partly cloudy</condition>
 <iconCode format="png">32</iconCode>
 <temperature unitType="metric" units="C">24</temperature>
 <lop category="Low" units="%">20</lop>
 <windChill unitType="metric"/>
 <humidex unitType="metric">32</humidex>
 <wind>
 <speed unitType="metric" units="km/h">10</speed>
 <direction windDirFull="Southwest">SW</direction>
 <gust unitType="metric" units="km/h"/>
 </wind>
 </hourlyForecast>
 <hourlyForecast dateTimeUTC="202106090400">
 <condition>Partly cloudy</condition>
 <iconCode format="png">32</iconCode>
 <temperature unitType="metric" units="C">23</temperature>
 <lop category="Low" units="%">20</lop>
 <windChill unitType="metric"/>
 <humidex unitType="metric">30</humidex>
 <wind>
 <speed unitType="metric" units="km/h">10</speed>
 <direction windDirFull="Southwest">SW</direction>
 <gust unitType="metric" units="km/h"/>
 </wind>
 </hourlyForecast>
 <hourlyForecast dateTimeUTC="202106090500">
 <condition>Partly cloudy</condition>
 <iconCode format="png">32</iconCode>
 <temperature unitType="metric" units="C">23</temperature>
 <lop category="Low" units="%">20</lop>
 <windChill unitType="metric"/>
 <humidex unitType="metric">29</humidex>
 <wind>
 <speed unitType="metric" units="km/h">10</speed>
 <direction windDirFull="Southwest">SW</direction>
 <gust unitType="metric" units="km/h"/>
 </wind>
 </hourlyForecast>
 <hourlyForecast dateTimeUTC="202106090600">
 <condition>A few clouds</condition>
 <iconCode format="png">31</iconCode>
 <temperature unitType="metric" units="C">22</temperature>
 <lop category="Low" units="%">20</lop>
 <windChill unitType="metric"/>
 <humidex unitType="metric">27</humidex>
 <wind>
 <speed unitType="metric" units="km/h">5</speed>
 <direction windDirFull="Variable direction">VR</direction>
 <gust unitType="metric" units="km/h"/>
 </wind>
 </hourlyForecast>
 <hourlyForecast dateTimeUTC="202106090700">
 <condition>A few clouds</condition>
 <iconCode format="png">31</iconCode>
 <temperature unitType="metric" units="C">21</temperature>
 <lop category="Low" units="%">20</lop>
 <windChill unitType="metric"/>
 <humidex unitType="metric">26</humidex>
 <wind>
 <speed unitType="metric" units="km/h">5</speed>
 <direction windDirFull="Variable direction">VR</direction>
 <gust unitType="metric" units="km/h"/>
 </wind>
 </hourlyForecast>
 <hourlyForecast dateTimeUTC="202106090800">
 <condition>A few clouds</condition>
 <iconCode format="png">31</iconCode>
 <temperature unitType="metric" units="C">21</temperature>
 <lop category="Low" units="%">20</lop>
 <windChill unitType="metric"/>
 <humidex unitType="metric">27</humidex>
 <wind>
 <speed unitType="metric" units="km/h">5</speed>
 <direction windDirFull="Variable direction">VR</direction>
 <gust unitType="metric" units="km/h"/>
 </wind>
 </hourlyForecast>
 <hourlyForecast dateTimeUTC="202106090900">
 <condition>A few clouds</condition>
 <iconCode format="png">31</iconCode>
 <temperature unitType="metric" units="C">20</temperature>
 <lop category="Low" units="%">20</lop>
 <windChill unitType="metric"/>
 <humidex unitType="metric">26</humidex>
 <wind>
 <speed unitType="metric" units="km/h">5</speed>
 <direction windDirFull="Variable direction">VR</direction>
 <gust unitType="metric" units="km/h"/>
 </wind>
 </hourlyForecast>
 <hourlyForecast dateTimeUTC="202106091000">
 <condition>Mainly sunny</condition>
 <iconCode format="png">01</iconCode>
 <temperature unitType="metric" units="C">21</temperature>
 <lop category="Low" units="%">20</lop>
 <windChill unitType="metric"/>
 <humidex unitType="metric">27</humidex>
 <wind>
 <speed unitType="metric" units="km/h">5</speed>
 <direction windDirFull="Variable direction">VR</direction>
 <gust unitType="metric" units="km/h"/>
 </wind>
 </hourlyForecast>
 <hourlyForecast dateTimeUTC="202106091100">
 <condition>Mainly sunny</condition>
 <iconCode format="png">01</iconCode>
 <temperature unitType="metric" units="C">22</temperature>
 <lop category="Low" units="%">20</lop>
 <windChill unitType="metric"/>
 <humidex unitType="metric">29</humidex>
 <wind>
 <speed unitType="metric" units="km/h">5</speed>
 <direction windDirFull="Variable direction">VR</direction>
 <gust unitType="metric" units="km/h"/>
 </wind>
 </hourlyForecast>
 <hourlyForecast dateTimeUTC="202106091200">
 <condition>Mainly sunny</condition>
 <iconCode format="png">01</iconCode>
 <temperature unitType="metric" units="C">23</temperature>
 <lop category="Low" units="%">20</lop>
 <windChill unitType="metric"/>
 <humidex unitType="metric">30</humidex>
 <wind>
 <speed unitType="metric" units="km/h">10</speed>
 <direction windDirFull="East">E</direction>
 <gust unitType="metric" units="km/h"/>
 </wind>
 </hourlyForecast>
 <hourlyForecast dateTimeUTC="202106091300">
 <condition>Mainly sunny</condition>
 <iconCode format="png">01</iconCode>
 <temperature unitType="metric" units="C">25</temperature>
 <lop category="Low" units="%">20</lop>
 <windChill unitType="metric"/>
 <humidex unitType="metric">32</humidex>
 <wind>
 <speed unitType="metric" units="km/h">10</speed>
 <direction windDirFull="East">E</direction>
 <gust unitType="metric" units="km/h"/>
 </wind>
 </hourlyForecast>
 <hourlyForecast dateTimeUTC="202106091400">
 <condition>Mainly sunny</condition>
 <iconCode format="png">01</iconCode>
 <temperature unitType="metric" units="C">27</temperature>
 <lop category="Low" units="%">20</lop>
 <windChill unitType="metric"/>
 <humidex unitType="metric">33</humidex>
 <wind>
 <speed unitType="metric" units="km/h">10</speed>
 <direction windDirFull="East">E</direction>
 <gust unitType="metric" units="km/h"/>
 </wind>
 </hourlyForecast>
 <hourlyForecast dateTimeUTC="202106091500">
 <condition>Mainly sunny</condition>
 <iconCode format="png">01</iconCode>
 <temperature unitType="metric" units="C">29</temperature>
 <lop category="Low" units="%">20</lop>
 <windChill unitType="metric"/>
 <humidex unitType="metric">35</humidex>
 <wind>
 <speed unitType="metric" units="km/h">10</speed>
 <direction windDirFull="East">E</direction>
 <gust unitType="metric" units="km/h"/>
 </wind>
 </hourlyForecast>
 <hourlyForecast dateTimeUTC="202106091600">
 <condition>Chance of showers</condition>
 <iconCode format="png">06</iconCode>
 <temperature unitType="metric" units="C">29</temperature>
 <lop category="Low" units="%">30</lop>
 <windChill unitType="metric"/>
 <humidex unitType="metric">35</humidex>
 <wind>
 <speed unitType="metric" units="km/h">10</speed>
 <direction windDirFull="East">E</direction>
 <gust unitType="metric" units="km/h"/>
 </wind>
 </hourlyForecast>
 <hourlyForecast dateTimeUTC="202106091700">
 <condition>Chance of showers</condition>
 <iconCode format="png">06</iconCode>
 <temperature unitType="metric" units="C">30</temperature>
 <lop category="Low" units="%">30</lop>
 <windChill unitType="metric"/>
 <humidex unitType="metric">37</humidex>
 <wind>
 <speed unitType="metric" units="km/h">10</speed>
 <direction windDirFull="East">E</direction>
 <gust unitType="metric" units="km/h"/>
 </wind>
 </hourlyForecast>
 </hourlyForecastGroup>
 <yesterdayConditions>
 <temperature unitType="metric" units="C" class="high">31.8</temperature>
 <temperature unitType="metric" units="C" class="low">19.6</temperature>
 <precip unitType="metric" units="mm">0.0</precip>
 </yesterdayConditions>
 <riseSet>
 <disclaimer>The information provided here, for the times of the rise and set of the sun, is an estimate included as a convenience to our clients. Values shown here may differ from the official sunrise/sunset data available from (http://hia-iha.nrc-cnrc.gc.ca/sunrise_e.html)</disclaimer>
 <dateTime name="sunrise" zone="UTC" UTCOffset="0">
 <year>2021</year>
 <month name="June">06</month>
 <day name="Tuesday">08</day>
 <hour>09</hour>
 <minute>36</minute>
 <timeStamp>20210608093600</timeStamp>
 <textSummary>Tuesday June 08, 2021 at 09:36 UTC</textSummary>
 </dateTime>
 <dateTime name="sunrise" zone="EDT" UTCOffset="-4">
 <year>2021</year>
 <month name="June">06</month>
 <day name="Tuesday">08</day>
 <hour>05</hour>
 <minute>36</minute>
 <timeStamp>20210608053600</timeStamp>
 <textSummary>Tuesday June 08, 2021 at 05:36 EDT</textSummary>
 </dateTime>
 <dateTime name="sunset" zone="UTC" UTCOffset="0">
 <year>2021</year>
 <month name="June">06</month>
 <day name="Wednesday">09</day>
 <hour>00</hour>
 <minute>57</minute>
 <timeStamp>20210609005700</timeStamp>
 <textSummary>Wednesday June 09, 2021 at 00:57 UTC</textSummary>
 </dateTime>
 <dateTime name="sunset" zone="EDT" UTCOffset="-4">
 <year>2021</year>
 <month name="June">06</month>
 <day name="Tuesday">08</day>
 <hour>20</hour>
 <minute>57</minute>
 <timeStamp>20210608205700</timeStamp>
 <textSummary>Tuesday June 08, 2021 at 20:57 EDT</textSummary>
 </dateTime>
 </riseSet>
 <almanac>
 <temperature class="extremeMax" period="1938-2013" unitType="metric" units="C" year="2011">33.4</temperature>
 <temperature class="extremeMin" period="1938-2013" unitType="metric" units="C" year="1949">0.6</temperature>
 <temperature class="normalMax" unitType="metric" units="C">22.7</temperature>
 <temperature class="normalMin" unitType="metric" units="C">10.8</temperature>
 <temperature class="normalMean" unitType="metric" units="C">16.8</temperature>
 <precipitation class="extremeRainfall" period="1938-2013" unitType="metric" units="mm" year="2003">17.6</precipitation>
 <precipitation class="extremeSnowfall" period="1938-2013" unitType="metric" units="cm" year="1938">0.0</precipitation>
 <precipitation class="extremePrecipitation" period="1938-2013" unitType="metric" units="mm" year="2003">17.6</precipitation>
 <precipitation class="extremeSnowOnGround" period="1955-2013" unitType="metric" units="cm" year="1955">0.0</precipitation>
 <pop units="%">36.0</pop>
 </almanac>
 </siteData>

